{
    "key": "group_62fc22180a589",
    "title": "Theme Colour Settings",
    "fields": [],
    "location": [
        [
            {
                "param": "options_page",
                "operator": "==",
                "value": "acf-options-colours"
            }
        ]
    ],
    "menu_order": 0,
    "position": "normal",
    "style": "default",
    "label_placement": "top",
    "instruction_placement": "label",
    "hide_on_screen": "",
    "active": true,
    "description": "",
    "show_in_rest": 0,
    "modified": 1660690984
}